opusgenie_di/__init__.py
opusgenie_di/__init__.pyi
opusgenie_di/py.typed
opusgenie_di/_base/__init__.py
opusgenie_di/_base/__init__.pyi
opusgenie_di/_base/component.py
opusgenie_di/_base/component.pyi
opusgenie_di/_base/enums.py
opusgenie_di/_base/enums.pyi
opusgenie_di/_base/metadata.py
opusgenie_di/_base/metadata.pyi
opusgenie_di/_base/protocols.py
opusgenie_di/_base/protocols.pyi
opusgenie_di/_core/__init__.py
opusgenie_di/_core/__init__.pyi
opusgenie_di/_core/container_impl.py
opusgenie_di/_core/container_impl.pyi
opusgenie_di/_core/container_interface.py
opusgenie_di/_core/container_interface.pyi
opusgenie_di/_core/context_impl.py
opusgenie_di/_core/context_impl.pyi
opusgenie_di/_core/context_interface.py
opusgenie_di/_core/context_interface.pyi
opusgenie_di/_core/event_loop_manager.py
opusgenie_di/_core/event_loop_manager.pyi
opusgenie_di/_core/exceptions.py
opusgenie_di/_core/exceptions.pyi
opusgenie_di/_core/global_context.py
opusgenie_di/_core/global_context.pyi
opusgenie_di/_core/provider_interface.py
opusgenie_di/_core/provider_interface.pyi
opusgenie_di/_core/scope_impl.py
opusgenie_di/_core/scope_impl.pyi
opusgenie_di/_core/scope_interface.py
opusgenie_di/_core/scope_interface.pyi
opusgenie_di/_decorators/__init__.py
opusgenie_di/_decorators/__init__.pyi
opusgenie_di/_decorators/component_decorator.py
opusgenie_di/_decorators/component_decorator.pyi
opusgenie_di/_decorators/context_decorator.py
opusgenie_di/_decorators/context_decorator.pyi
opusgenie_di/_decorators/decorator_options.py
opusgenie_di/_decorators/decorator_options.pyi
opusgenie_di/_decorators/decorator_utils.py
opusgenie_di/_decorators/decorator_utils.pyi
opusgenie_di/_hooks/__init__.py
opusgenie_di/_hooks/__init__.pyi
opusgenie_di/_hooks/event_hooks.py
opusgenie_di/_hooks/event_hooks.pyi
opusgenie_di/_hooks/hook_manager.py
opusgenie_di/_hooks/hook_manager.pyi
opusgenie_di/_hooks/lifecycle_hooks.py
opusgenie_di/_hooks/lifecycle_hooks.pyi
opusgenie_di/_modules/__init__.py
opusgenie_di-0.1.8.dist-info/licenses/LICENSE
opusgenie_di-0.1.8.dist-info/METADATA
opusgenie_di-0.1.8.dist-info/WHEEL
opusgenie_di-0.1.8.dist-info/top_level.txt
opusgenie_di-0.1.8.dist-info/RECORD
