Metadata-Version: 2.4
Name: opusgenie-di
Version: 0.1.8
Summary: A powerful, multi-context dependency injection framework for Python with comprehensive async lifecycle management
Author: Abhishek Pathak
License-Expression: Apache-2.0
Project-URL: Homepage, https://github.com/krabhishek/opusgenie-di
Project-URL: Repository, https://github.com/krabhishek/opusgenie-di
Project-URL: Bug Tracker, https://github.com/krabhishek/opusgenie-di/issues
Project-URL: Documentation, https://github.com/krabhishek/opusgenie-di#readme
Project-URL: Changelog, https://github.com/krabhishek/opusgenie-di/releases
Keywords: dependency-injection,di,inversion-of-control,ioc,framework,python,multi-context,angular-style,type-safe,async,lifecycle-management,event-driven
Classifier: Development Status :: 4 - Beta
Classifier: Intended Audience :: Developers
Classifier: Operating System :: OS Independent
Classifier: Programming Language :: Python :: 3
Classifier: Programming Language :: Python :: 3.12
Classifier: Programming Language :: Python :: 3.13
Classifier: Topic :: Software Development :: Libraries :: Python Modules
Classifier: Topic :: Software Development :: Libraries :: Application Frameworks
Classifier: Topic :: System :: Systems Administration
Classifier: Typing :: Typed
Requires-Python: >=3.12
License-File: LICENSE
Requires-Dist: dependency-injector>=4.46.0
Requires-Dist: pydantic>=2.11.5
Requires-Dist: structlog>=25.3.0
Requires-Dist: typing-extensions>=4.0.0
Dynamic: license-file
